{"expireTime":9007200910765524000,"key":"gatsby-plugin-mdx-entire-payload-b7ca5e976a4cc641c5e3f3aafaaee819-","val":{"mdast":{"type":"root","children":[{"type":"import","value":"import DefaultLayout from \"/home/runner/work/unittestbot.github.io/unittestbot.github.io/node_modules/gatsby-theme-docz/src/base/Layout.js\"","position":{"start":{"line":3,"column":1,"offset":2},"end":{"line":3,"column":140,"offset":141},"indent":[]}},{"type":"export","default":true,"value":"export default DefaultLayout","position":{"start":{"line":5,"column":1,"offset":143},"end":{"line":5,"column":29,"offset":171},"indent":[]}},{"type":"heading","depth":1,"children":[{"type":"text","value":"FAQ","position":{"start":{"line":8,"column":3,"offset":176},"end":{"line":8,"column":6,"offset":179},"indent":[]}}],"position":{"start":{"line":8,"column":1,"offset":174},"end":{"line":8,"column":6,"offset":179},"indent":[]}},{"type":"heading","depth":3,"children":[{"type":"text","value":"UTBot fails to build from docker","position":{"start":{"line":10,"column":5,"offset":185},"end":{"line":10,"column":37,"offset":217},"indent":[]}}],"position":{"start":{"line":10,"column":1,"offset":181},"end":{"line":10,"column":37,"offset":217},"indent":[]}},{"type":"list","ordered":false,"start":null,"spread":false,"children":[{"type":"listItem","spread":false,"checked":null,"children":[{"type":"paragraph","children":[{"type":"text","value":"invoke ","position":{"start":{"line":12,"column":3,"offset":221},"end":{"line":12,"column":10,"offset":228},"indent":[]}},{"type":"inlineCode","value":"source ~/.runtime_env.sh","position":{"start":{"line":12,"column":10,"offset":228},"end":{"line":12,"column":36,"offset":254},"indent":[]}},{"type":"text","value":" shell command and try again.","position":{"start":{"line":12,"column":36,"offset":254},"end":{"line":12,"column":65,"offset":283},"indent":[]}}],"position":{"start":{"line":12,"column":3,"offset":221},"end":{"line":12,"column":65,"offset":283},"indent":[]}}],"position":{"start":{"line":12,"column":1,"offset":219},"end":{"line":12,"column":65,"offset":283},"indent":[]}}],"position":{"start":{"line":12,"column":1,"offset":219},"end":{"line":12,"column":65,"offset":283},"indent":[]}},{"type":"heading","depth":3,"children":[{"type":"text","value":"Quickstart Wizard tab did not open when you launched the plugin","position":{"start":{"line":14,"column":5,"offset":289},"end":{"line":14,"column":68,"offset":352},"indent":[]}}],"position":{"start":{"line":14,"column":1,"offset":285},"end":{"line":14,"column":68,"offset":352},"indent":[]}},{"type":"list","ordered":false,"start":null,"spread":false,"children":[{"type":"listItem","spread":false,"checked":null,"children":[{"type":"paragraph","children":[{"type":"text","value":"in VSCode inovke  ","position":{"start":{"line":16,"column":3,"offset":356},"end":{"line":16,"column":21,"offset":374},"indent":[]}},{"type":"inlineCode","value":"Run UTBot: Quickstart Wizard","position":{"start":{"line":16,"column":21,"offset":374},"end":{"line":16,"column":51,"offset":404},"indent":[]}},{"type":"text","value":" command from the Command pallette ","position":{"start":{"line":16,"column":51,"offset":404},"end":{"line":16,"column":86,"offset":439},"indent":[]}},{"type":"inlineCode","value":"Shift + Ctrl + P","position":{"start":{"line":16,"column":86,"offset":439},"end":{"line":16,"column":104,"offset":457},"indent":[]}},{"type":"text","value":" or ","position":{"start":{"line":16,"column":104,"offset":457},"end":{"line":16,"column":108,"offset":461},"indent":[]}},{"type":"inlineCode","value":"F1","position":{"start":{"line":16,"column":108,"offset":461},"end":{"line":16,"column":112,"offset":465},"indent":[]}}],"position":{"start":{"line":16,"column":3,"offset":356},"end":{"line":16,"column":112,"offset":465},"indent":[]}}],"position":{"start":{"line":16,"column":1,"offset":354},"end":{"line":16,"column":112,"offset":465},"indent":[]}}],"position":{"start":{"line":16,"column":1,"offset":354},"end":{"line":16,"column":112,"offset":465},"indent":[]}},{"type":"heading","depth":3,"children":[{"type":"text","value":"Source file is not registered: /path/to/file/filename.c","position":{"start":{"line":18,"column":5,"offset":471},"end":{"line":18,"column":60,"offset":526},"indent":[]}}],"position":{"start":{"line":18,"column":1,"offset":467},"end":{"line":18,"column":60,"offset":526},"indent":[]}},{"type":"list","ordered":false,"start":null,"spread":false,"children":[{"type":"listItem","spread":false,"checked":null,"children":[{"type":"paragraph","children":[{"type":"text","value":"Open ","position":{"start":{"line":20,"column":3,"offset":530},"end":{"line":20,"column":8,"offset":535},"indent":[]}},{"type":"inlineCode","value":"UTBot explorer","position":{"start":{"line":20,"column":8,"offset":535},"end":{"line":20,"column":24,"offset":551},"indent":[]}},{"type":"text","value":" from left corner or press F1 and type ","position":{"start":{"line":20,"column":24,"offset":551},"end":{"line":20,"column":63,"offset":590},"indent":[]}},{"type":"inlineCode","value":"View: Show UTBot explorer","position":{"start":{"line":20,"column":63,"offset":590},"end":{"line":20,"column":90,"offset":617},"indent":[]}}],"position":{"start":{"line":20,"column":3,"offset":530},"end":{"line":20,"column":90,"offset":617},"indent":[]}}],"position":{"start":{"line":20,"column":1,"offset":528},"end":{"line":20,"column":90,"offset":617},"indent":[]}},{"type":"listItem","spread":false,"checked":null,"children":[{"type":"paragraph","children":[{"type":"text","value":"In ","position":{"start":{"line":21,"column":3,"offset":620},"end":{"line":21,"column":6,"offset":623},"indent":[]}},{"type":"inlineCode","value":"UTBOT FOLDERS","position":{"start":{"line":21,"column":6,"offset":623},"end":{"line":21,"column":21,"offset":638},"indent":[]}},{"type":"text","value":" mark source as UTBot Source Folder\n","position":{"start":{"line":21,"column":21,"offset":638},"end":{"line":22,"column":3,"offset":676},"indent":[3]}},{"type":"inlineCode","value":"src","position":{"start":{"line":22,"column":3,"offset":676},"end":{"line":22,"column":8,"offset":681},"indent":[]}},{"type":"text","value":", ","position":{"start":{"line":22,"column":8,"offset":681},"end":{"line":22,"column":10,"offset":683},"indent":[]}},{"type":"inlineCode","value":"lib","position":{"start":{"line":22,"column":10,"offset":683},"end":{"line":22,"column":15,"offset":688},"indent":[]}},{"type":"text","value":", ","position":{"start":{"line":22,"column":15,"offset":688},"end":{"line":22,"column":17,"offset":690},"indent":[]}},{"type":"inlineCode","value":"build\\src","position":{"start":{"line":22,"column":17,"offset":690},"end":{"line":22,"column":28,"offset":701},"indent":[]}},{"type":"text","value":", ","position":{"start":{"line":22,"column":28,"offset":701},"end":{"line":22,"column":30,"offset":703},"indent":[]}},{"type":"inlineCode","value":"build\\lib","position":{"start":{"line":22,"column":30,"offset":703},"end":{"line":22,"column":41,"offset":714},"indent":[]}}],"position":{"start":{"line":21,"column":3,"offset":620},"end":{"line":22,"column":41,"offset":714},"indent":[3]}}],"position":{"start":{"line":21,"column":1,"offset":618},"end":{"line":22,"column":41,"offset":714},"indent":[1]}}],"position":{"start":{"line":20,"column":1,"offset":528},"end":{"line":22,"column":41,"offset":714},"indent":[1,1]}},{"type":"heading","depth":3,"children":[{"type":"text","value":"File not found in compilation_commands.json","position":{"start":{"line":24,"column":5,"offset":720},"end":{"line":24,"column":48,"offset":763},"indent":[]}}],"position":{"start":{"line":24,"column":1,"offset":716},"end":{"line":24,"column":48,"offset":763},"indent":[]}},{"type":"list","ordered":false,"start":null,"spread":false,"children":[{"type":"listItem","spread":false,"checked":null,"children":[{"type":"paragraph","children":[{"type":"text","value":"in VSCode inovke  ","position":{"start":{"line":26,"column":3,"offset":767},"end":{"line":26,"column":21,"offset":785},"indent":[]}},{"type":"inlineCode","value":"UTBot: Reset cache and configure project","position":{"start":{"line":26,"column":21,"offset":785},"end":{"line":26,"column":63,"offset":827},"indent":[]}},{"type":"text","value":" command from the Command pallette ","position":{"start":{"line":26,"column":63,"offset":827},"end":{"line":26,"column":98,"offset":862},"indent":[]}},{"type":"inlineCode","value":"Shift + Ctrl + P","position":{"start":{"line":26,"column":98,"offset":862},"end":{"line":26,"column":116,"offset":880},"indent":[]}},{"type":"text","value":"\nor ","position":{"start":{"line":26,"column":116,"offset":880},"end":{"line":27,"column":6,"offset":886},"indent":[3]}},{"type":"inlineCode","value":"F1","position":{"start":{"line":27,"column":6,"offset":886},"end":{"line":27,"column":10,"offset":890},"indent":[]}}],"position":{"start":{"line":26,"column":3,"offset":767},"end":{"line":27,"column":10,"offset":890},"indent":[3]}}],"position":{"start":{"line":26,"column":1,"offset":765},"end":{"line":27,"column":10,"offset":890},"indent":[1]}}],"position":{"start":{"line":26,"column":1,"offset":765},"end":{"line":27,"column":10,"offset":890},"indent":[1]}},{"type":"heading","depth":3,"children":[{"type":"text","value":"bear make -j","position":{"start":{"line":29,"column":5,"offset":896},"end":{"line":29,"column":17,"offset":908},"indent":[]}}],"position":{"start":{"line":29,"column":1,"offset":892},"end":{"line":29,"column":17,"offset":908},"indent":[]}},{"type":"list","ordered":false,"start":null,"spread":false,"children":[{"type":"listItem","spread":false,"checked":null,"children":[{"type":"paragraph","children":[{"type":"text","value":"in VSCode inovke  ","position":{"start":{"line":31,"column":3,"offset":912},"end":{"line":31,"column":21,"offset":930},"indent":[]}},{"type":"inlineCode","value":"UTBot: Reset cache and configure project","position":{"start":{"line":31,"column":21,"offset":930},"end":{"line":31,"column":63,"offset":972},"indent":[]}},{"type":"text","value":" command from the Command pallette ","position":{"start":{"line":31,"column":63,"offset":972},"end":{"line":31,"column":98,"offset":1007},"indent":[]}},{"type":"inlineCode","value":"Shift + Ctrl + P","position":{"start":{"line":31,"column":98,"offset":1007},"end":{"line":31,"column":116,"offset":1025},"indent":[]}},{"type":"text","value":"\nor ","position":{"start":{"line":31,"column":116,"offset":1025},"end":{"line":32,"column":6,"offset":1031},"indent":[3]}},{"type":"inlineCode","value":"F1","position":{"start":{"line":32,"column":6,"offset":1031},"end":{"line":32,"column":10,"offset":1035},"indent":[]}}],"position":{"start":{"line":31,"column":3,"offset":912},"end":{"line":32,"column":10,"offset":1035},"indent":[3]}}],"position":{"start":{"line":31,"column":1,"offset":910},"end":{"line":32,"column":10,"offset":1035},"indent":[1]}}],"position":{"start":{"line":31,"column":1,"offset":910},"end":{"line":32,"column":10,"offset":1035},"indent":[1]}},{"type":"heading","depth":3,"children":[{"type":"text","value":"UNAVAILABLE: No connection established in vscode","position":{"start":{"line":34,"column":5,"offset":1041},"end":{"line":34,"column":53,"offset":1089},"indent":[]}}],"position":{"start":{"line":34,"column":1,"offset":1037},"end":{"line":34,"column":53,"offset":1089},"indent":[]}},{"type":"list","ordered":false,"start":null,"spread":false,"children":[{"type":"listItem","spread":false,"checked":null,"children":[{"type":"paragraph","children":[{"type":"text","value":"Check if utbot server is up","position":{"start":{"line":36,"column":3,"offset":1093},"end":{"line":36,"column":30,"offset":1120},"indent":[]}}],"position":{"start":{"line":36,"column":3,"offset":1093},"end":{"line":36,"column":30,"offset":1120},"indent":[]}}],"position":{"start":{"line":36,"column":1,"offset":1091},"end":{"line":36,"column":30,"offset":1120},"indent":[]}},{"type":"listItem","spread":false,"checked":null,"children":[{"type":"paragraph","children":[{"type":"text","value":"in VSCode inovke ","position":{"start":{"line":37,"column":3,"offset":1123},"end":{"line":37,"column":20,"offset":1140},"indent":[]}},{"type":"inlineCode","value":"Developer: Reload Window","position":{"start":{"line":37,"column":20,"offset":1140},"end":{"line":37,"column":46,"offset":1166},"indent":[]}},{"type":"text","value":" command from the Command pallette ","position":{"start":{"line":37,"column":46,"offset":1166},"end":{"line":37,"column":81,"offset":1201},"indent":[]}},{"type":"inlineCode","value":"Shift + Ctrl + P","position":{"start":{"line":37,"column":81,"offset":1201},"end":{"line":37,"column":99,"offset":1219},"indent":[]}},{"type":"text","value":" or ","position":{"start":{"line":37,"column":99,"offset":1219},"end":{"line":37,"column":103,"offset":1223},"indent":[]}},{"type":"inlineCode","value":"F1","position":{"start":{"line":37,"column":103,"offset":1223},"end":{"line":37,"column":107,"offset":1227},"indent":[]}}],"position":{"start":{"line":37,"column":3,"offset":1123},"end":{"line":37,"column":107,"offset":1227},"indent":[]}}],"position":{"start":{"line":37,"column":1,"offset":1121},"end":{"line":37,"column":107,"offset":1227},"indent":[]}}],"position":{"start":{"line":36,"column":1,"offset":1091},"end":{"line":37,"column":107,"offset":1227},"indent":[1]}},{"type":"heading","depth":3,"children":[{"type":"text","value":"No logs, or incorrect logs","position":{"start":{"line":39,"column":5,"offset":1233},"end":{"line":39,"column":31,"offset":1259},"indent":[]}}],"position":{"start":{"line":39,"column":1,"offset":1229},"end":{"line":39,"column":31,"offset":1259},"indent":[]}},{"type":"list","ordered":false,"start":null,"spread":false,"children":[{"type":"listItem","spread":false,"checked":null,"children":[{"type":"paragraph","children":[{"type":"text","value":"kill all utbot server instance and run new one.\n","position":{"start":{"line":41,"column":3,"offset":1263},"end":{"line":42,"column":3,"offset":1313},"indent":[3]}},{"type":"inlineCode","value":"ps aux | grep \"utbot server\" | grep -v grep | awk '{print $2;}' | xargs kill","position":{"start":{"line":42,"column":3,"offset":1313},"end":{"line":42,"column":81,"offset":1391},"indent":[]}}],"position":{"start":{"line":41,"column":3,"offset":1263},"end":{"line":42,"column":81,"offset":1391},"indent":[3]}}],"position":{"start":{"line":41,"column":1,"offset":1261},"end":{"line":42,"column":81,"offset":1391},"indent":[1]}}],"position":{"start":{"line":41,"column":1,"offset":1261},"end":{"line":42,"column":81,"offset":1391},"indent":[1]}},{"type":"export","value":"export const _frontmatter = {}","position":{"start":{"line":44,"column":1,"offset":1393},"end":{"line":44,"column":31,"offset":1423},"indent":[]}}],"position":{"start":{"line":1,"column":1,"offset":0},"end":{"line":44,"column":31,"offset":1423}}},"scopeImports":[],"scopeIdentifiers":[],"rawMDXOutput":"/* @jsx mdx */\nimport { mdx } from '@mdx-js/react';\n/* @jsxRuntime classic */\n/* @jsx mdx */\nimport DefaultLayout from \"/home/runner/work/unittestbot.github.io/unittestbot.github.io/node_modules/gatsby-theme-docz/src/base/Layout.js\"\nexport const _frontmatter = {};\n\nconst layoutProps = {\n  _frontmatter\n};\nconst MDXLayout = DefaultLayout\nexport default function MDXContent({\n  components,\n  ...props\n}) {\n  return <MDXLayout {...layoutProps} {...props} components={components} mdxType=\"MDXLayout\">\n\n\n    <h1 {...{\n      \"id\": \"faq\"\n    }}>{`FAQ`}</h1>\n    <h3 {...{\n      \"id\": \"utbot-fails-to-build-from-docker\"\n    }}>{`UTBot fails to build from docker`}</h3>\n    <ul>\n      <li parentName=\"ul\">{`invoke `}<inlineCode parentName=\"li\">{`source ~/.runtime_env.sh`}</inlineCode>{` shell command and try again.`}</li>\n    </ul>\n    <h3 {...{\n      \"id\": \"quickstart-wizard-tab-did-not-open-when-you-launched-the-plugin\"\n    }}>{`Quickstart Wizard tab did not open when you launched the plugin`}</h3>\n    <ul>\n      <li parentName=\"ul\">{`in VSCode inovke  `}<inlineCode parentName=\"li\">{`Run UTBot: Quickstart Wizard`}</inlineCode>{` command from the Command pallette `}<inlineCode parentName=\"li\">{`Shift + Ctrl + P`}</inlineCode>{` or `}<inlineCode parentName=\"li\">{`F1`}</inlineCode></li>\n    </ul>\n    <h3 {...{\n      \"id\": \"source-file-is-not-registered-pathtofilefilenamec\"\n    }}>{`Source file is not registered: /path/to/file/filename.c`}</h3>\n    <ul>\n      <li parentName=\"ul\">{`Open `}<inlineCode parentName=\"li\">{`UTBot explorer`}</inlineCode>{` from left corner or press F1 and type `}<inlineCode parentName=\"li\">{`View: Show UTBot explorer`}</inlineCode></li>\n      <li parentName=\"ul\">{`In `}<inlineCode parentName=\"li\">{`UTBOT FOLDERS`}</inlineCode>{` mark source as UTBot Source Folder\n`}<inlineCode parentName=\"li\">{`src`}</inlineCode>{`, `}<inlineCode parentName=\"li\">{`lib`}</inlineCode>{`, `}<inlineCode parentName=\"li\">{`build\\\\src`}</inlineCode>{`, `}<inlineCode parentName=\"li\">{`build\\\\lib`}</inlineCode></li>\n    </ul>\n    <h3 {...{\n      \"id\": \"file-not-found-in-compilation_commandsjson\"\n    }}>{`File not found in compilation_commands.json`}</h3>\n    <ul>\n      <li parentName=\"ul\">{`in VSCode inovke  `}<inlineCode parentName=\"li\">{`UTBot: Reset cache and configure project`}</inlineCode>{` command from the Command pallette `}<inlineCode parentName=\"li\">{`Shift + Ctrl + P`}</inlineCode>{`\nor `}<inlineCode parentName=\"li\">{`F1`}</inlineCode></li>\n    </ul>\n    <h3 {...{\n      \"id\": \"bear-make--j\"\n    }}>{`bear make -j`}</h3>\n    <ul>\n      <li parentName=\"ul\">{`in VSCode inovke  `}<inlineCode parentName=\"li\">{`UTBot: Reset cache and configure project`}</inlineCode>{` command from the Command pallette `}<inlineCode parentName=\"li\">{`Shift + Ctrl + P`}</inlineCode>{`\nor `}<inlineCode parentName=\"li\">{`F1`}</inlineCode></li>\n    </ul>\n    <h3 {...{\n      \"id\": \"unavailable-no-connection-established-in-vscode\"\n    }}>{`UNAVAILABLE: No connection established in vscode`}</h3>\n    <ul>\n      <li parentName=\"ul\">{`Check if utbot server is up`}</li>\n      <li parentName=\"ul\">{`in VSCode inovke `}<inlineCode parentName=\"li\">{`Developer: Reload Window`}</inlineCode>{` command from the Command pallette `}<inlineCode parentName=\"li\">{`Shift + Ctrl + P`}</inlineCode>{` or `}<inlineCode parentName=\"li\">{`F1`}</inlineCode></li>\n    </ul>\n    <h3 {...{\n      \"id\": \"no-logs-or-incorrect-logs\"\n    }}>{`No logs, or incorrect logs`}</h3>\n    <ul>\n      <li parentName=\"ul\">{`kill all utbot server instance and run new one.\n`}<inlineCode parentName=\"li\">{`ps aux | grep \"utbot server\" | grep -v grep | awk '{print $2;}' | xargs kill`}</inlineCode></li>\n    </ul>\n\n    </MDXLayout>;\n}\n\n;\nMDXContent.isMDXComponent = true;"}}